{
    "Type 1": [
        {
            "name": "L'Oreal Hyaluron Moisture Shampoo",
            "brand": "L'Oreal Paris",
            "image": "https://m.media-amazon.com/images/I/51+6q+P+VJL._SL1000_.jpg",
            "link": "https://www.amazon.in/s?k=L%27Oreal+Paris+Hyaluron+Moisture+Shampoo"
        },
        {
            "name": "Biolage Smoothproof Conditioner",
            "brand": "Matrix",
            "image": "https://m.media-amazon.com/images/I/51pK-jW-cIL._SL1000_.jpg",
            "link": "https://www.amazon.in/s?k=Biolage+Smoothproof+Conditioner"
        }
    ],
    "Type 2": [
        {
            "name": "Kevin Murphy Killer Waves",
            "brand": "Kevin Murphy",
            "image": "https://m.media-amazon.com/images/I/61j1-C-O0EL._SL1500_.jpg",
            "link": "https://www.amazon.in/s?k=Kevin+Murphy+Killer+Waves"
        },
        {
            "name": "Livon Shake & Spray Serum",
            "brand": "Livon",
            "image": "https://m.media-amazon.com/images/I/41K-m8o8iSL._SX300_SY300_QL70_FMwebp_.jpg",
            "link": "https://www.amazon.in/s?k=Livon+Shake+and+Spray+Serum"
        }
    ],
    "Type 3": [
        {
            "name": "Advanced Curl Care Hair Cream",
            "brand": "Arata",
            "image": "https://m.media-amazon.com/images/I/61RCNt+j+oL._SL1080_.jpg",
            "link": "https://www.amazon.in/s?k=Arata+Advanced+Curl+Care+Hair+Cream"
        },
        {
            "name": "Fix My Curls Leave-in Cream",
            "brand": "Fix My Curls",
            "image": "https://m.media-amazon.com/images/I/51A3I4qN+JL._SL1000_.jpg",
            "link": "https://www.amazon.in/s?k=Fix+My+Curls+Leave-in+Cream"
        }
    ],
    "Type 4": [
        {
            "name": "Shea Butter & Coconut Curling Cream",
            "brand": "Cantu",
            "image": "https://m.media-amazon.com/images/I/71u+2e+g+pL._SL1500_.jpg",
            "link": "https://www.amazon.in/s?k=Cantu+Shea+Butter+Coconut+Curling+Cream"
        },
        {
            "name": "Jamaica Black Castor Oil Masque",
            "brand": "Shea Moisture",
            "image": "https://m.media-amazon.com/images/I/81I-1a+iW+L._SL1500_.jpg",
            "link": "https://www.amazon.in/s?k=Shea+Moisture+Jamaican+Black+Castor+Oil+Masque"
        }
    ]
}
